mdscan/__init__.py
mdscan/__main__.py
mdscan/analysis.py
mdscan/clusterize.py
mdscan/qmst.py
mdscan/trajload.py
mdscan/vantage.py
mdscan-0.0.3.dist-info/LICENSE
mdscan-0.0.3.dist-info/METADATA
mdscan-0.0.3.dist-info/WHEEL
mdscan-0.0.3.dist-info/entry_points.txt
mdscan-0.0.3.dist-info/top_level.txt
mdscan-0.0.3.dist-info/RECORD
