Metadata-Version: 2.1
Name: mdscan
Version: 0.0.3
Summary: RMSD-Based HDBSCAN Clustering of Long Molecular Dynamics
Home-page: https://github.com/LQCT/MDScan.git
Author: Roy González-Alemán
Author-email: roy_gonzalez@fq.uh.cu
Classifier: Programming Language :: Python :: 3
Classifier: Programming Language :: Python :: 3.9
License-File: LICENSE
Requires-Dist: numpy (==1.21)
Requires-Dist: numba (>=0.55)
Requires-Dist: mdtraj (>=1.9.5)
Requires-Dist: numpy-indexed (>=0.3)
Requires-Dist: pandas (>=1.4)
